stampy/main.py
stampy-0.1.3.dist-info/entry_points.txt
stampy-0.1.3.dist-info/WHEEL
stampy-0.1.3.dist-info/METADATA
stampy-0.1.3.dist-info/RECORD
