Metadata-Version: 2.1
Name: stampy
Version: 0.1.3
Summary: ４文字の文字列をスタンプ風画像に変換するツール 
Author: Comamoca
Author-email: comamoca.dev@gmail.com
Requires-Python: >=3.10,<4.0
Classifier: Programming Language :: Python :: 3
Classifier: Programming Language :: Python :: 3.10
Requires-Dist: Pillow (>=9.2.0,<10.0.0)
Requires-Dist: click (>=8.1.3,<9.0.0)
